ShopLineAPI-12.0.1.data/scripts/shopline_api.py
shopline/__init__.py
shopline/api_access.py
shopline/api_version.py
shopline/base.py
shopline/collection.py
shopline/connection.py
shopline/mixins.py
shopline/session.py
shopline/version.py
shopline/yamlobjects.py
shopline/resources/__init__.py
shopline/resources/customers.py
shopline/resources/merchants.py
shopline/resources/orders.py
shopline/resources/products.py
shopline/resources/sales.py
shopline/utils/__init__.py
shopline/utils/authorize.py
shopline/utils/formats.py
shopline/utils/utils.py
ShopLineAPI-12.0.1.dist-info/LICENSE
ShopLineAPI-12.0.1.dist-info/METADATA
ShopLineAPI-12.0.1.dist-info/WHEEL
ShopLineAPI-12.0.1.dist-info/top_level.txt
ShopLineAPI-12.0.1.dist-info/RECORD
